raver/__init__.py
raver/__main__.py
raver/cli.py
raver-3.0.2.dist-info/LICENSE
raver-3.0.2.dist-info/METADATA
raver-3.0.2.dist-info/WHEEL
raver-3.0.2.dist-info/entry_points.txt
raver-3.0.2.dist-info/RECORD
