Metadata-Version: 2.1
Name: raver
Version: 3.0.2
Summary: Ratio package management tool.
Home-page: https://gitlab.com/ratio-case/python/raver
License: MIT
Author: Ratio Innovations B.V.
Author-email: info@ratio-case.nl
Requires-Python: >=3.9,<4.0
Classifier: License :: OSI Approved :: MIT License
Classifier: Programming Language :: Python :: 3
Classifier: Programming Language :: Python :: 3.9
Classifier: Programming Language :: Python :: 3.10
Classifier: Programming Language :: Python :: 3.11
Classifier: Programming Language :: Python :: 3.12
Requires-Dist: click (>=8,<9)
Requires-Dist: semver (>=3,<4)
Requires-Dist: tomli (>=2,<3)
Project-URL: Documentation, https://raver.ratio-case.nl
Project-URL: Repository, https://gitlab.com/ratio-case/python/raver
